pykitti/__init__.py
pykitti/odometry.py
pykitti/raw.py
pykitti/utils.py
pykitti-0.3.0.dist-info/DESCRIPTION.rst
pykitti-0.3.0.dist-info/METADATA
pykitti-0.3.0.dist-info/RECORD
pykitti-0.3.0.dist-info/WHEEL
pykitti-0.3.0.dist-info/metadata.json
pykitti-0.3.0.dist-info/top_level.txt
